handler.py
rsyslog_fix.py
setup.py
syslogprocessor.py
SyslogProcessor.egg-info/PKG-INFO
SyslogProcessor.egg-info/SOURCES.txt
SyslogProcessor.egg-info/dependency_links.txt
SyslogProcessor.egg-info/requires.txt
SyslogProcessor.egg-info/top_level.txt
scripts/syslogprocessor