Metadata-Version: 1.0
Name: SyslogProcessor
Version: 0.1.0
Summary: Syslog processing framework
Home-page: http://github.com/greghaynes/SyslogProcessor
Author: Gregory Haynes
Author-email: greg@greghaynes.net
License: MIT
Platform: UNKNOWN
